setup.py
pipages/__init__.py
pipages/_config.py
pipages/path.py
pipages/pipages.py
pipages/piweb.py
pipages.egg-info/PKG-INFO
pipages.egg-info/SOURCES.txt
pipages.egg-info/dependency_links.txt
pipages.egg-info/entry_points.txt
pipages.egg-info/requires.txt
pipages.egg-info/top_level.txt