Metadata-Version: 1.0
Name: pipages
Version: 0.1.0
Summary: GitHub pages like system for managing static websites.
Home-page: http://github.com/anandology/pipages
Author: Anand Chitipothu
Author-email: anandology@gmail.com
License: BSD
Platform: any
